Metadata-Version: 2.1
Name: biglake
Version: 0.1
Summary: Create and query datalakes
Home-page: https://github.com/anthonypotappel/biglake
Author: Anthony Potappel
Author-email: anthony.potappel@gmail.com
License: UNKNOWN
Platform: UNKNOWN
Classifier: Operating System :: POSIX :: Linux
Classifier: License :: OSI Approved :: MIT License
Classifier: Programming Language :: Python :: 3.5
Classifier: Programming Language :: Python :: 3.6
Classifier: Programming Language :: Python :: 3.7
